{"country": "SDN", "n_predictions": 12, "predictions": [{"admin_code": "SDN_Kassala", "country": "SDN", "crop": "sorghum", "year": 2023, "prediction": 1, "stress_probability": 1.0, "risk_score": 100.0, "ndvi_mean": 0.092, "ndvi_min": 0.089, "n_months": 5, "centroid": [0, 0]}, {"admin_code": "SDN_Gedaref", "country": "SDN", "crop": "sorghum", "year": 2023, "prediction": 1, "stress_probability": 1.0, "risk_score": 100.0, "ndvi_mean": 0.12, "ndvi_min": 0.063, "n_months": 7, "centroid": [0, 0]}, {"admin_code": "SDN_Gezira", "country": "SDN", "crop": "wheat", "year": 2023, "prediction": 0, "stress_probability": 0.001, "risk_score": 0.1, "ndvi_mean": 0.228, "ndvi_min": 0.077, "n_months": 20, "centroid": [0, 0]}, {"admin_code": "SDN_Gezira", "country": "SDN", "crop": "wheat", "year": 2022, "prediction": 1, "stress_probability": 1.0, "risk_score": 100.0, "ndvi_mean": 0.111, "ndvi_min": 0.072, "n_months": 28, "centroid": [0, 0]}, {"admin_code": "SDN_Kassala", "country": "SDN", "crop": "sorghum", "year": 2022, "prediction": 1, "stress_probability": 1.0, "risk_score": 100.0, "ndvi_mean": 0.097, "ndvi_min": 0.086, "n_months": 24, "centroid": [0, 0]}, {"admin_code": "SDN_Gedaref", "country": "SDN", "crop": "sorghum", "year": 2022, "prediction": 1, "stress_probability": 1.0, "risk_score": 100.0, "ndvi_mean": 0.096, "ndvi_min": 0.062, "n_months": 9, "centroid": [0, 0]}, {"admin_code": "SDN_Kassala", "country": "SDN", "crop": "sorghum", "year": 2021, "prediction": 1, "stress_probability": 1.0, "risk_score": 100.0, "ndvi_mean": 0.14, "ndvi_min": 0.121, "n_months": 28, "centroid": [0, 0]}, {"admin_code": "SDN_Gezira", "country": "SDN", "crop": "wheat", "year": 2021, "prediction": 0, "stress_probability": 0.0, "risk_score": 0.0, "ndvi_mean": 0.285, "ndvi_min": 0.121, "n_months": 24, "centroid": [0, 0]}, {"admin_code": "SDN_Gedaref", "country": "SDN", "crop": "sorghum", "year": 2021, "prediction": 0, "stress_probability": 0.0, "risk_score": 0.0, "ndvi_mean": 0.156, "ndvi_min": 0.102, "n_months": 24, "centroid": [0, 0]}, {"admin_code": "SDN_Kassala", "country": "SDN", "crop": "sorghum", "year": 2020, "prediction": 1, "stress_probability": 1.0, "risk_score": 100.0, "ndvi_mean": 0.142, "ndvi_min": 0.108, "n_months": 28, "centroid": [0, 0]}, {"admin_code": "SDN_Gezira", "country": "SDN", "crop": "wheat", "year": 2020, "prediction": 0, "stress_probability": 0.0, "risk_score": 0.0, "ndvi_mean": 0.208, "ndvi_min": 0.121, "n_months": 24, "centroid": [0, 0]}, {"admin_code": "SDN_Gedaref", "country": "SDN", "crop": "sorghum", "year": 2020, "prediction": 0, "stress_probability": 0.0, "risk_score": 0.0, "ndvi_mean": 0.172, "ndvi_min": 0.1, "n_months": 28, "centroid": [0, 0]}]}