{"country": "TZA", "n_predictions": 16, "predictions": [{"admin_code": "TZA_Mbeya", "country": "TZA", "crop": "corn", "year": 2023, "prediction": 1, "stress_probability": 1.0, "risk_score": 100.0, "ndvi_mean": 0.121, "ndvi_min": 0.096, "n_months": 28, "centroid": [0, 0]}, {"admin_code": "TZA_Iringa", "country": "TZA", "crop": "corn", "year": 2023, "prediction": 0, "stress_probability": 0.001, "risk_score": 0.1, "ndvi_mean": 0.161, "ndvi_min": 0.015, "n_months": 28, "centroid": [0, 0]}, {"admin_code": "TZA_Morogoro", "country": "TZA", "crop": "rice", "year": 2023, "prediction": 0, "stress_probability": 0.0, "risk_score": 0.0, "ndvi_mean": 0.201, "ndvi_min": 0.152, "n_months": 24, "centroid": [0, 0]}, {"admin_code": "TZA_Rukwa", "country": "TZA", "crop": "corn", "year": 2023, "prediction": 0, "stress_probability": 0.0, "risk_score": 0.0, "ndvi_mean": 0.233, "ndvi_min": 0.155, "n_months": 28, "centroid": [0, 0]}, {"admin_code": "TZA_Mbeya", "country": "TZA", "crop": "corn", "year": 2022, "prediction": 1, "stress_probability": 1.0, "risk_score": 100.0, "ndvi_mean": 0.112, "ndvi_min": 0.097, "n_months": 28, "centroid": [0, 0]}, {"admin_code": "TZA_Iringa", "country": "TZA", "crop": "corn", "year": 2022, "prediction": 0, "stress_probability": 0.0, "risk_score": 0.0, "ndvi_mean": 0.185, "ndvi_min": 0.126, "n_months": 28, "centroid": [0, 0]}, {"admin_code": "TZA_Morogoro", "country": "TZA", "crop": "rice", "year": 2022, "prediction": 0, "stress_probability": 0.0, "risk_score": 0.0, "ndvi_mean": 0.172, "ndvi_min": 0.131, "n_months": 24, "centroid": [0, 0]}, {"admin_code": "TZA_Rukwa", "country": "TZA", "crop": "corn", "year": 2022, "prediction": 0, "stress_probability": 0.0, "risk_score": 0.0, "ndvi_mean": 0.239, "ndvi_min": 0.16, "n_months": 28, "centroid": [0, 0]}, {"admin_code": "TZA_Iringa", "country": "TZA", "crop": "corn", "year": 2021, "prediction": 0, "stress_probability": 0.0, "risk_score": 0.0, "ndvi_mean": 0.285, "ndvi_min": 0.192, "n_months": 28, "centroid": [0, 0]}, {"admin_code": "TZA_Mbeya", "country": "TZA", "crop": "corn", "year": 2021, "prediction": 0, "stress_probability": 0.0, "risk_score": 0.0, "ndvi_mean": 0.189, "ndvi_min": 0.145, "n_months": 28, "centroid": [0, 0]}, {"admin_code": "TZA_Morogoro", "country": "TZA", "crop": "rice", "year": 2021, "prediction": 0, "stress_probability": 0.0, "risk_score": 0.0, "ndvi_mean": 0.268, "ndvi_min": 0.24, "n_months": 24, "centroid": [0, 0]}, {"admin_code": "TZA_Rukwa", "country": "TZA", "crop": "corn", "year": 2021, "prediction": 0, "stress_probability": 0.0, "risk_score": 0.0, "ndvi_mean": 0.432, "ndvi_min": 0.327, "n_months": 28, "centroid": [0, 0]}, {"admin_code": "TZA_Iringa", "country": "TZA", "crop": "corn", "year": 2020, "prediction": 0, "stress_probability": 0.0, "risk_score": 0.0, "ndvi_mean": 0.319, "ndvi_min": 0.21, "n_months": 28, "centroid": [0, 0]}, {"admin_code": "TZA_Mbeya", "country": "TZA", "crop": "corn", "year": 2020, "prediction": 0, "stress_probability": 0.0, "risk_score": 0.0, "ndvi_mean": 0.194, "ndvi_min": 0.152, "n_months": 28, "centroid": [0, 0]}, {"admin_code": "TZA_Rukwa", "country": "TZA", "crop": "corn", "year": 2020, "prediction": 0, "stress_probability": 0.0, "risk_score": 0.0, "ndvi_mean": 0.409, "ndvi_min": 0.319, "n_months": 28, "centroid": [0, 0]}, {"admin_code": "TZA_Morogoro", "country": "TZA", "crop": "rice", "year": 2020, "prediction": 0, "stress_probability": 0.0, "risk_score": 0.0, "ndvi_mean": 0.259, "ndvi_min": 0.212, "n_months": 28, "centroid": [0, 0]}]}